{"v":3,"stories":{"ring-ui-welcome--getting-started":{"id":"ring-ui-welcome--getting-started","name":"Getting Started","title":"Ring UI/Welcome","importPath":"./src/welcome.stories.tsx","tags":["story"],"kind":"Ring UI/Welcome","story":"Getting Started","parameters":{"__id":"ring-ui-welcome--getting-started","docsOnly":false,"fileName":"./src/welcome.stories.tsx"}},"ring-ui-welcome--contributing":{"id":"ring-ui-welcome--contributing","name":"Contributing","title":"Ring UI/Welcome","importPath":"./src/welcome.stories.tsx","tags":["story"],"kind":"Ring UI/Welcome","story":"Contributing","parameters":{"__id":"ring-ui-welcome--contributing","docsOnly":false,"fileName":"./src/welcome.stories.tsx"}},"ring-ui-welcome--changelog":{"id":"ring-ui-welcome--changelog","name":"Changelog","title":"Ring UI/Welcome","importPath":"./src/welcome.stories.tsx","tags":["story"],"kind":"Ring UI/Welcome","story":"Changelog","parameters":{"__id":"ring-ui-welcome--changelog","docsOnly":false,"fileName":"./src/welcome.stories.tsx"}},"ring-ui-welcome--license":{"id":"ring-ui-welcome--license","name":"License","title":"Ring UI/Welcome","importPath":"./src/welcome.stories.tsx","tags":["story"],"kind":"Ring UI/Welcome","story":"License","parameters":{"__id":"ring-ui-welcome--license","docsOnly":false,"fileName":"./src/welcome.stories.tsx"}},"services-alert-service--alert-service":{"id":"services-alert-service--alert-service","name":"Alert Service","title":"Services/Alert Service","importPath":"./src/alert-service/alert-service.stories.tsx","tags":["story"],"kind":"Services/Alert Service","story":"Alert Service","parameters":{"__id":"services-alert-service--alert-service","docsOnly":false,"fileName":"./src/alert-service/alert-service.stories.tsx"}},"components-alert--simple":{"id":"components-alert--simple","name":"simple","title":"Components/Alert","importPath":"./src/alert/alert.stories.tsx","tags":["story"],"kind":"Components/Alert","story":"simple","parameters":{"__id":"components-alert--simple","docsOnly":false,"fileName":"./src/alert/alert.stories.tsx"}},"components-alert--alert-container":{"id":"components-alert--alert-container","name":"Alert Container","title":"Components/Alert","importPath":"./src/alert/alert.stories.tsx","tags":["story"],"kind":"Components/Alert","story":"Alert Container","parameters":{"__id":"components-alert--alert-container","docsOnly":false,"fileName":"./src/alert/alert.stories.tsx"}},"components-analytics--analytics":{"id":"components-analytics--analytics","name":"Analytics","title":"Components/Analytics","importPath":"./src/analytics/analytics.stories.tsx","tags":["story"],"kind":"Components/Analytics","story":"Analytics","parameters":{"__id":"components-analytics--analytics","docsOnly":false,"fileName":"./src/analytics/analytics.stories.tsx"}},"services-auth-dialog-service--auth-dialog-service":{"id":"services-auth-dialog-service--auth-dialog-service","name":"Auth Dialog Service","title":"Services/Auth Dialog Service","importPath":"./src/auth-dialog-service/auth-dialog-service.stories.tsx","tags":["story"],"kind":"Services/Auth Dialog Service","story":"Auth Dialog Service","parameters":{"__id":"services-auth-dialog-service--auth-dialog-service","docsOnly":false,"fileName":"./src/auth-dialog-service/auth-dialog-service.stories.tsx"}},"components-auth-dialog--auth-dialog":{"id":"components-auth-dialog--auth-dialog","name":"Auth Dialog","title":"Components/Auth Dialog","importPath":"./src/auth-dialog/auth-dialog.stories.tsx","tags":["story"],"kind":"Components/Auth Dialog","story":"Auth Dialog","parameters":{"__id":"components-auth-dialog--auth-dialog","docsOnly":false,"fileName":"./src/auth-dialog/auth-dialog.stories.tsx"}},"utilities-auth--basic":{"id":"utilities-auth--basic","name":"basic","title":"Utilities/Auth","importPath":"./src/auth/auth.stories.tsx","tags":["story"],"kind":"Utilities/Auth","story":"basic","parameters":{"__id":"utilities-auth--basic","docsOnly":false,"fileName":"./src/auth/auth.stories.tsx"}},"utilities-auth--in-i-frame":{"id":"utilities-auth--in-i-frame","name":"in IFrame","title":"Utilities/Auth","importPath":"./src/auth/auth.stories.tsx","tags":["story"],"kind":"Utilities/Auth","story":"in IFrame","parameters":{"__id":"utilities-auth--in-i-frame","docsOnly":false,"fileName":"./src/auth/auth.stories.tsx"}},"components-avatar--avatar":{"id":"components-avatar--avatar","name":"Avatar","title":"Components/Avatar","importPath":"./src/avatar/avatar.stories.tsx","tags":["story"],"kind":"Components/Avatar","story":"Avatar","parameters":{"__id":"components-avatar--avatar","docsOnly":false,"fileName":"./src/avatar/avatar.stories.tsx"}},"components-badge--badge":{"id":"components-badge--badge","name":"Badge","title":"Components/Badge","importPath":"./src/badge/badge.stories.tsx","tags":["story"],"kind":"Components/Badge","story":"Badge","parameters":{"__id":"components-badge--badge","docsOnly":false,"fileName":"./src/badge/badge.stories.tsx"}},"components-button-group--button-group":{"id":"components-button-group--button-group","name":"Button Group","title":"Components/Button Group","importPath":"./src/button-group/button-group.stories.tsx","tags":["story"],"kind":"Components/Button Group","story":"Button Group","parameters":{"__id":"components-button-group--button-group","docsOnly":false,"fileName":"./src/button-group/button-group.stories.tsx"}},"components-button-set--button-set":{"id":"components-button-set--button-set","name":"Button Set","title":"Components/Button Set","importPath":"./src/button-set/button-set.stories.tsx","tags":["story"],"kind":"Components/Button Set","story":"Button Set","parameters":{"__id":"components-button-set--button-set","docsOnly":false,"fileName":"./src/button-set/button-set.stories.tsx"}},"components-button-toolbar--button-toolbar":{"id":"components-button-toolbar--button-toolbar","name":"Button Toolbar","title":"Components/Button Toolbar","importPath":"./src/button-toolbar/button-toolbar.stories.tsx","tags":["story"],"kind":"Components/Button Toolbar","story":"Button Toolbar","parameters":{"__id":"components-button-toolbar--button-toolbar","docsOnly":false,"fileName":"./src/button-toolbar/button-toolbar.stories.tsx"}},"components-button--single":{"id":"components-button--single","name":"Single","title":"Components/Button","importPath":"./src/button/button.stories.tsx","tags":["story"],"kind":"Components/Button","story":"Single","parameters":{"__id":"components-button--single","docsOnly":false,"fileName":"./src/button/button.stories.tsx"}},"components-button--basic":{"id":"components-button--basic","name":"basic","title":"Components/Button","importPath":"./src/button/button.stories.tsx","tags":["story"],"kind":"Components/Button","story":"basic","parameters":{"__id":"components-button--basic","docsOnly":false,"fileName":"./src/button/button.stories.tsx"}},"components-button--height-s":{"id":"components-button--height-s","name":"Height S","title":"Components/Button","importPath":"./src/button/button.stories.tsx","tags":["story"],"kind":"Components/Button","story":"Height S","parameters":{"__id":"components-button--height-s","docsOnly":false,"fileName":"./src/button/button.stories.tsx"}},"components-button--height-l":{"id":"components-button--height-l","name":"Height L","title":"Components/Button","importPath":"./src/button/button.stories.tsx","tags":["story"],"kind":"Components/Button","story":"Height L","parameters":{"__id":"components-button--height-l","docsOnly":false,"fileName":"./src/button/button.stories.tsx"}},"components-button--long-action":{"id":"components-button--long-action","name":"long action","title":"Components/Button","importPath":"./src/button/button.stories.tsx","tags":["story"],"kind":"Components/Button","story":"long action","parameters":{"__id":"components-button--long-action","docsOnly":false,"fileName":"./src/button/button.stories.tsx"}},"utilities-caret--basic":{"id":"utilities-caret--basic","name":"Caret","title":"Utilities/Caret","importPath":"./src/caret/caret.stories.tsx","tags":["story"],"kind":"Utilities/Caret","story":"Caret","parameters":{"__id":"utilities-caret--basic","docsOnly":false,"fileName":"./src/caret/caret.stories.tsx"}},"components-checkbox--controls":{"id":"components-checkbox--controls","name":"Controls","title":"Components/Checkbox","importPath":"./src/checkbox/checkbox.stories.tsx","tags":["story"],"kind":"Components/Checkbox","story":"Controls","parameters":{"__id":"components-checkbox--controls","docsOnly":false,"fileName":"./src/checkbox/checkbox.stories.tsx"}},"components-checkbox--basic":{"id":"components-checkbox--basic","name":"basic","title":"Components/Checkbox","importPath":"./src/checkbox/checkbox.stories.tsx","tags":["story"],"kind":"Components/Checkbox","story":"basic","parameters":{"__id":"components-checkbox--basic","docsOnly":false,"fileName":"./src/checkbox/checkbox.stories.tsx"}},"components-clipboard--copy-to-clipboard":{"id":"components-clipboard--copy-to-clipboard","name":"Copy To Clipboard","title":"Components/Clipboard","importPath":"./src/clipboard/clipboard.stories.tsx","tags":["story"],"kind":"Components/Clipboard","story":"Copy To Clipboard","parameters":{"__id":"components-clipboard--copy-to-clipboard","docsOnly":false,"fileName":"./src/clipboard/clipboard.stories.tsx"}},"components-code--basic":{"id":"components-code--basic","name":"basic","title":"Components/Code","importPath":"./src/code/code.stories.tsx","tags":["story"],"kind":"Components/Code","story":"basic","parameters":{"__id":"components-code--basic","docsOnly":false,"fileName":"./src/code/code.stories.tsx"}},"components-code--lazy":{"id":"components-code--lazy","name":"Lazy","title":"Components/Code","importPath":"./src/code/code.stories.tsx","tags":["story"],"kind":"Components/Code","story":"Lazy","parameters":{"__id":"components-code--lazy","docsOnly":false,"fileName":"./src/code/code.stories.tsx"}},"components-code--tagged-template":{"id":"components-code--tagged-template","name":"tagged template","title":"Components/Code","importPath":"./src/code/code.stories.tsx","tags":["story"],"kind":"Components/Code","story":"tagged template","parameters":{"__id":"components-code--tagged-template","docsOnly":false,"fileName":"./src/code/code.stories.tsx"}},"services-confirm-service--confirm-service":{"id":"services-confirm-service--confirm-service","name":"Confirm Service","title":"Services/Confirm Service","importPath":"./src/confirm-service/confirm-service.stories.tsx","tags":["story"],"kind":"Services/Confirm Service","story":"Confirm Service","parameters":{"__id":"services-confirm-service--confirm-service","docsOnly":false,"fileName":"./src/confirm-service/confirm-service.stories.tsx"}},"components-confirm--confirm":{"id":"components-confirm--confirm","name":"Confirm","title":"Components/Confirm","importPath":"./src/confirm/confirm.stories.tsx","tags":["story"],"kind":"Components/Confirm","story":"Confirm","parameters":{"__id":"components-confirm--confirm","docsOnly":false,"fileName":"./src/confirm/confirm.stories.tsx"}},"components-content-layout--basic":{"id":"components-content-layout--basic","name":"basic","title":"Components/Content Layout","importPath":"./src/content-layout/content-layout.stories.tsx","tags":["story"],"kind":"Components/Content Layout","story":"basic","parameters":{"__id":"components-content-layout--basic","docsOnly":false,"fileName":"./src/content-layout/content-layout.stories.tsx"}},"components-content-layout--with-sidebar-on-the-left":{"id":"components-content-layout--with-sidebar-on-the-left","name":"with sidebar on the left","title":"Components/Content Layout","importPath":"./src/content-layout/content-layout.stories.tsx","tags":["story"],"kind":"Components/Content Layout","story":"with sidebar on the left","parameters":{"__id":"components-content-layout--with-sidebar-on-the-left","docsOnly":false,"fileName":"./src/content-layout/content-layout.stories.tsx"}},"components-content-layout--with-sidebar-on-the-right":{"id":"components-content-layout--with-sidebar-on-the-right","name":"with sidebar on the right","title":"Components/Content Layout","importPath":"./src/content-layout/content-layout.stories.tsx","tags":["story"],"kind":"Components/Content Layout","story":"with sidebar on the right","parameters":{"__id":"components-content-layout--with-sidebar-on-the-right","docsOnly":false,"fileName":"./src/content-layout/content-layout.stories.tsx"}},"components-contenteditable--basic":{"id":"components-contenteditable--basic","name":"ContentEditable","title":"Components/ContentEditable","importPath":"./src/contenteditable/contenteditable.stories.tsx","tags":["story"],"kind":"Components/ContentEditable","story":"ContentEditable","parameters":{"__id":"components-contenteditable--basic","docsOnly":false,"fileName":"./src/contenteditable/contenteditable.stories.tsx"}},"components-datalist--basic":{"id":"components-datalist--basic","name":"DataList","title":"Components/DataList","importPath":"./src/data-list/data-list.stories.tsx","tags":["story"],"kind":"Components/DataList","story":"DataList","parameters":{"__id":"components-datalist--basic","docsOnly":false,"fileName":"./src/data-list/data-list.stories.tsx"}},"components-date-picker--single-date":{"id":"components-date-picker--single-date","name":"single date","title":"Components/Date Picker","importPath":"./src/date-picker/date-picker.stories.tsx","tags":["story"],"kind":"Components/Date Picker","story":"single date","parameters":{"__id":"components-date-picker--single-date","docsOnly":false,"fileName":"./src/date-picker/date-picker.stories.tsx"}},"components-date-picker--single-date-and-time":{"id":"components-date-picker--single-date-and-time","name":"single date and time","title":"Components/Date Picker","importPath":"./src/date-picker/date-picker.stories.tsx","tags":["story"],"kind":"Components/Date Picker","story":"single date and time","parameters":{"__id":"components-date-picker--single-date-and-time","docsOnly":false,"fileName":"./src/date-picker/date-picker.stories.tsx"}},"components-date-picker--range":{"id":"components-date-picker--range","name":"range","title":"Components/Date Picker","importPath":"./src/date-picker/date-picker.stories.tsx","tags":["story"],"kind":"Components/Date Picker","story":"range","parameters":{"__id":"components-date-picker--range","docsOnly":false,"fileName":"./src/date-picker/date-picker.stories.tsx"}},"components-date-picker--clearable":{"id":"components-date-picker--clearable","name":"clearable","title":"Components/Date Picker","importPath":"./src/date-picker/date-picker.stories.tsx","tags":["story"],"kind":"Components/Date Picker","story":"clearable","parameters":{"__id":"components-date-picker--clearable","docsOnly":false,"fileName":"./src/date-picker/date-picker.stories.tsx"}},"components-date-picker--single-with-min-max":{"id":"components-date-picker--single-with-min-max","name":"single with min-max dates","title":"Components/Date Picker","importPath":"./src/date-picker/date-picker.stories.tsx","tags":["story"],"kind":"Components/Date Picker","story":"single with min-max dates","parameters":{"__id":"components-date-picker--single-with-min-max","docsOnly":false,"fileName":"./src/date-picker/date-picker.stories.tsx"}},"components-date-picker--single-with-min":{"id":"components-date-picker--single-with-min","name":"single with min date","title":"Components/Date Picker","importPath":"./src/date-picker/date-picker.stories.tsx","tags":["story"],"kind":"Components/Date Picker","story":"single with min date","parameters":{"__id":"components-date-picker--single-with-min","docsOnly":false,"fileName":"./src/date-picker/date-picker.stories.tsx"}},"components-date-picker--single-with-max":{"id":"components-date-picker--single-with-max","name":"single with max date","title":"Components/Date Picker","importPath":"./src/date-picker/date-picker.stories.tsx","tags":["story"],"kind":"Components/Date Picker","story":"single with max date","parameters":{"__id":"components-date-picker--single-with-max","docsOnly":false,"fileName":"./src/date-picker/date-picker.stories.tsx"}},"components-date-picker--range-with-min-max":{"id":"components-date-picker--range-with-min-max","name":"range with min-max dates","title":"Components/Date Picker","importPath":"./src/date-picker/date-picker.stories.tsx","tags":["story"],"kind":"Components/Date Picker","story":"range with min-max dates","parameters":{"__id":"components-date-picker--range-with-min-max","docsOnly":false,"fileName":"./src/date-picker/date-picker.stories.tsx"}},"components-date-picker--range-with-min":{"id":"components-date-picker--range-with-min","name":"range with min date","title":"Components/Date Picker","importPath":"./src/date-picker/date-picker.stories.tsx","tags":["story"],"kind":"Components/Date Picker","story":"range with min date","parameters":{"__id":"components-date-picker--range-with-min","docsOnly":false,"fileName":"./src/date-picker/date-picker.stories.tsx"}},"components-date-picker--range-with-max":{"id":"components-date-picker--range-with-max","name":"range with max date","title":"Components/Date Picker","importPath":"./src/date-picker/date-picker.stories.tsx","tags":["story"],"kind":"Components/Date Picker","story":"range with max date","parameters":{"__id":"components-date-picker--range-with-max","docsOnly":false,"fileName":"./src/date-picker/date-picker.stories.tsx"}},"components-date-picker--range-with-custom-placeholders":{"id":"components-date-picker--range-with-custom-placeholders","name":"range with customized placeholders","title":"Components/Date Picker","importPath":"./src/date-picker/date-picker.stories.tsx","tags":["story"],"kind":"Components/Date Picker","story":"range with customized placeholders","parameters":{"__id":"components-date-picker--range-with-custom-placeholders","docsOnly":false,"fileName":"./src/date-picker/date-picker.stories.tsx"}},"components-date-picker--render-inline":{"id":"components-date-picker--render-inline","name":"inline","title":"Components/Date Picker","importPath":"./src/date-picker/date-picker.stories.tsx","tags":["story"],"kind":"Components/Date Picker","story":"inline","parameters":{"__id":"components-date-picker--render-inline","docsOnly":false,"fileName":"./src/date-picker/date-picker.stories.tsx"}},"components-date-picker--all-sizes":{"id":"components-date-picker--all-sizes","name":"all sizes","title":"Components/Date Picker","importPath":"./src/date-picker/date-picker.stories.tsx","tags":["story"],"kind":"Components/Date Picker","story":"all sizes","parameters":{"__id":"components-date-picker--all-sizes","docsOnly":false,"fileName":"./src/date-picker/date-picker.stories.tsx"}},"components-dialog--basic":{"id":"components-dialog--basic","name":"basic","title":"Components/Dialog","importPath":"./src/dialog/dialog.stories.tsx","tags":["story"],"kind":"Components/Dialog","story":"basic","parameters":{"__id":"components-dialog--basic","docsOnly":false,"fileName":"./src/dialog/dialog.stories.tsx"}},"components-dialog--dense":{"id":"components-dialog--dense","name":"Dense","title":"Components/Dialog","importPath":"./src/dialog/dialog.stories.tsx","tags":["story"],"kind":"Components/Dialog","story":"Dense","parameters":{"__id":"components-dialog--dense","docsOnly":false,"fileName":"./src/dialog/dialog.stories.tsx"}},"components-dialog--with-scroll":{"id":"components-dialog--with-scroll","name":"with scroll","title":"Components/Dialog","importPath":"./src/dialog/dialog.stories.tsx","tags":["story"],"kind":"Components/Dialog","story":"with scroll","parameters":{"__id":"components-dialog--with-scroll","docsOnly":false,"fileName":"./src/dialog/dialog.stories.tsx"}},"components-dialog--with-overflow-scroll-on-html":{"id":"components-dialog--with-overflow-scroll-on-html","name":"With Overflow Scroll On Html","title":"Components/Dialog","importPath":"./src/dialog/dialog.stories.tsx","tags":["story"],"kind":"Components/Dialog","story":"With Overflow Scroll On Html","parameters":{"__id":"components-dialog--with-overflow-scroll-on-html","docsOnly":false,"fileName":"./src/dialog/dialog.stories.tsx"}},"components-dropdownmenu--basic":{"id":"components-dropdownmenu--basic","name":"DropdownMenu","title":"Components/DropdownMenu","importPath":"./src/dropdown-menu/dropdown-menu.stories.tsx","tags":["story"],"kind":"Components/DropdownMenu","story":"DropdownMenu","parameters":{"__id":"components-dropdownmenu--basic","docsOnly":false,"fileName":"./src/dropdown-menu/dropdown-menu.stories.tsx"}},"components-dropdown--basic":{"id":"components-dropdown--basic","name":"basic","title":"Components/Dropdown","importPath":"./src/dropdown/dropdown.stories.tsx","tags":["story"],"kind":"Components/Dropdown","story":"basic","parameters":{"__id":"components-dropdown--basic","docsOnly":false,"fileName":"./src/dropdown/dropdown.stories.tsx"}},"components-dropdown--with-custom-anchor-and-popup":{"id":"components-dropdown--with-custom-anchor-and-popup","name":"with custom anchor and popup","title":"Components/Dropdown","importPath":"./src/dropdown/dropdown.stories.tsx","tags":["story"],"kind":"Components/Dropdown","story":"with custom anchor and popup","parameters":{"__id":"components-dropdown--with-custom-anchor-and-popup","docsOnly":false,"fileName":"./src/dropdown/dropdown.stories.tsx"}},"components-dropdown--with-custom-anchor-and-popup-and-content-accessibility-handling":{"id":"components-dropdown--with-custom-anchor-and-popup-and-content-accessibility-handling","name":"With Custom Anchor And Popup And Content Accessibility Handling","title":"Components/Dropdown","importPath":"./src/dropdown/dropdown.stories.tsx","tags":["story"],"kind":"Components/Dropdown","story":"With Custom Anchor And Popup And Content Accessibility Handling","parameters":{"__id":"components-dropdown--with-custom-anchor-and-popup-and-content-accessibility-handling","docsOnly":false,"fileName":"./src/dropdown/dropdown.stories.tsx"}},"components-dropdown--with-active-class-name":{"id":"components-dropdown--with-active-class-name","name":"with activeClassName","title":"Components/Dropdown","importPath":"./src/dropdown/dropdown.stories.tsx","tags":["story"],"kind":"Components/Dropdown","story":"with activeClassName","parameters":{"__id":"components-dropdown--with-active-class-name","docsOnly":false,"fileName":"./src/dropdown/dropdown.stories.tsx"}},"components-dropdown--with-hover-mode":{"id":"components-dropdown--with-hover-mode","name":"with hover mode","title":"Components/Dropdown","importPath":"./src/dropdown/dropdown.stories.tsx","tags":["story"],"kind":"Components/Dropdown","story":"with hover mode","parameters":{"__id":"components-dropdown--with-hover-mode","docsOnly":false,"fileName":"./src/dropdown/dropdown.stories.tsx"}},"components-dropdown--with-hover-mode-and-disabled-click-mode":{"id":"components-dropdown--with-hover-mode-and-disabled-click-mode","name":"with hover mode and disabled click mode","title":"Components/Dropdown","importPath":"./src/dropdown/dropdown.stories.tsx","tags":["story"],"kind":"Components/Dropdown","story":"with hover mode and disabled click mode","parameters":{"__id":"components-dropdown--with-hover-mode-and-disabled-click-mode","docsOnly":false,"fileName":"./src/dropdown/dropdown.stories.tsx"}},"components-dropdown--autofocus-on-open":{"id":"components-dropdown--autofocus-on-open","name":"autofocus on open","title":"Components/Dropdown","importPath":"./src/dropdown/dropdown.stories.tsx","tags":["story"],"kind":"Components/Dropdown","story":"autofocus on open","parameters":{"__id":"components-dropdown--autofocus-on-open","docsOnly":false,"fileName":"./src/dropdown/dropdown.stories.tsx"}},"components-dropdown--render-props":{"id":"components-dropdown--render-props","name":"Render Props","title":"Components/Dropdown","importPath":"./src/dropdown/dropdown.stories.tsx","tags":["story"],"kind":"Components/Dropdown","story":"Render Props","parameters":{"__id":"components-dropdown--render-props","docsOnly":false,"fileName":"./src/dropdown/dropdown.stories.tsx"}},"components-editable-heading--basic":{"id":"components-editable-heading--basic","name":"Editable Heading","title":"Components/Editable Heading","importPath":"./src/editable-heading/editable-heading.stories.tsx","tags":["story"],"kind":"Components/Editable Heading","story":"Editable Heading","parameters":{"__id":"components-editable-heading--basic","docsOnly":false,"fileName":"./src/editable-heading/editable-heading.stories.tsx"}},"components-errorbubble--basic":{"id":"components-errorbubble--basic","name":"basic","title":"Components/ErrorBubble","importPath":"./src/error-bubble/error-bubble.stories.tsx","tags":["story"],"kind":"Components/ErrorBubble","story":"basic","parameters":{"__id":"components-errorbubble--basic","docsOnly":false,"fileName":"./src/error-bubble/error-bubble.stories.tsx"}},"components-errorbubble--in-dialog-form":{"id":"components-errorbubble--in-dialog-form","name":"in dialog form","title":"Components/ErrorBubble","importPath":"./src/error-bubble/error-bubble.stories.tsx","tags":["story"],"kind":"Components/ErrorBubble","story":"in dialog form","parameters":{"__id":"components-errorbubble--in-dialog-form","docsOnly":false,"fileName":"./src/error-bubble/error-bubble.stories.tsx"}},"components-error-message--basic":{"id":"components-error-message--basic","name":"Error Message","title":"Components/Error Message","importPath":"./src/error-message/error-message.stories.tsx","tags":["story"],"kind":"Components/Error Message","story":"Error Message","parameters":{"__id":"components-error-message--basic","docsOnly":false,"fileName":"./src/error-message/error-message.stories.tsx"}},"components-footer--basic":{"id":"components-footer--basic","name":"Footer","title":"Components/Footer","importPath":"./src/footer/footer.stories.tsx","tags":["story"],"kind":"Components/Footer","story":"Footer","parameters":{"__id":"components-footer--basic","docsOnly":false,"fileName":"./src/footer/footer.stories.tsx"}},"style-only-form--basic":{"id":"style-only-form--basic","name":"Form","title":"Style-only/Form","importPath":"./src/form/form.stories.js","tags":["story"],"kind":"Style-only/Form","story":"Form","parameters":{"__id":"style-only-form--basic","docsOnly":false,"fileName":"./src/form/form.stories.js"}},"utilities-dom--basic":{"id":"utilities-dom--basic","name":"DOM","title":"Utilities/DOM","importPath":"./src/global/dom.stories.tsx","tags":["story"],"kind":"Utilities/DOM","story":"DOM","parameters":{"__id":"utilities-dom--basic","docsOnly":false,"fileName":"./src/global/dom.stories.tsx"}},"components-theme-provider--basic":{"id":"components-theme-provider--basic","name":"Theme Provider","title":"Components/Theme Provider","importPath":"./src/global/theme.stories.tsx","tags":["story"],"kind":"Components/Theme Provider","story":"Theme Provider","parameters":{"__id":"components-theme-provider--basic","docsOnly":false,"fileName":"./src/global/theme.stories.tsx"}},"components-theme-provider--with-popup":{"id":"components-theme-provider--with-popup","name":"Theme Provider and Popup","title":"Components/Theme Provider","importPath":"./src/global/theme.stories.tsx","tags":["story"],"kind":"Components/Theme Provider","story":"Theme Provider and Popup","parameters":{"__id":"components-theme-provider--with-popup","docsOnly":false,"fileName":"./src/global/theme.stories.tsx"}},"style-only-theme-palette--basic":{"id":"style-only-theme-palette--basic","name":"Theme palette","title":"Style-only/Theme palette","importPath":"./src/global/variables.stories.tsx","tags":["story"],"kind":"Style-only/Theme palette","story":"Theme palette","parameters":{"__id":"style-only-theme-palette--basic","docsOnly":false,"fileName":"./src/global/variables.stories.tsx"}},"components-grid--responsive":{"id":"components-grid--responsive","name":"responsive","title":"Components/Grid","importPath":"./src/grid/grid.stories.tsx","tags":["story"],"kind":"Components/Grid","story":"responsive","parameters":{"__id":"components-grid--responsive","docsOnly":false,"fileName":"./src/grid/grid.stories.tsx"}},"components-grid--offset":{"id":"components-grid--offset","name":"offset","title":"Components/Grid","importPath":"./src/grid/grid.stories.tsx","tags":["story"],"kind":"Components/Grid","story":"offset","parameters":{"__id":"components-grid--offset","docsOnly":false,"fileName":"./src/grid/grid.stories.tsx"}},"components-grid--auto-size":{"id":"components-grid--auto-size","name":"auto size","title":"Components/Grid","importPath":"./src/grid/grid.stories.tsx","tags":["story"],"kind":"Components/Grid","story":"auto size","parameters":{"__id":"components-grid--auto-size","docsOnly":false,"fileName":"./src/grid/grid.stories.tsx"}},"components-grid--alignment":{"id":"components-grid--alignment","name":"alignment","title":"Components/Grid","importPath":"./src/grid/grid.stories.tsx","tags":["story"],"kind":"Components/Grid","story":"alignment","parameters":{"__id":"components-grid--alignment","docsOnly":false,"fileName":"./src/grid/grid.stories.tsx"}},"components-grid--columns-distribution":{"id":"components-grid--columns-distribution","name":"columns distribution","title":"Components/Grid","importPath":"./src/grid/grid.stories.tsx","tags":["story"],"kind":"Components/Grid","story":"columns distribution","parameters":{"__id":"components-grid--columns-distribution","docsOnly":false,"fileName":"./src/grid/grid.stories.tsx"}},"components-group--basic":{"id":"components-group--basic","name":"Group","title":"Components/Group","importPath":"./src/group/group.stories.tsx","tags":["story"],"kind":"Components/Group","story":"Group","parameters":{"__id":"components-group--basic","docsOnly":false,"fileName":"./src/group/group.stories.tsx"}},"components-header--header":{"id":"components-header--header","name":"Header","title":"Components/Header","importPath":"./src/header/header.stories.tsx","tags":["story"],"kind":"Components/Header","story":"Header","parameters":{"__id":"components-header--header","docsOnly":false,"fileName":"./src/header/header.stories.tsx"}},"components-heading--basic":{"id":"components-heading--basic","name":"Heading","title":"Components/Heading","importPath":"./src/heading/heading.stories.tsx","tags":["story"],"kind":"Components/Heading","story":"Heading","parameters":{"__id":"components-heading--basic","docsOnly":false,"fileName":"./src/heading/heading.stories.tsx"}},"utilities-http-service--basic":{"id":"utilities-http-service--basic","name":"HTTP service","title":"Utilities/HTTP service","importPath":"./src/http/http.stories.tsx","tags":["story"],"kind":"Utilities/HTTP service","story":"HTTP service","parameters":{"__id":"utilities-http-service--basic","docsOnly":false,"fileName":"./src/http/http.stories.tsx"}},"services-i18n--basic":{"id":"services-i18n--basic","name":"basic","title":"Services/I18n","importPath":"./src/i18n/i18n.stories.tsx","tags":["story"],"kind":"Services/I18n","story":"basic","parameters":{"__id":"services-i18n--basic","docsOnly":false,"fileName":"./src/i18n/i18n.stories.tsx"}},"components-icon--basic":{"id":"components-icon--basic","name":"basic","title":"Components/Icon","importPath":"./src/icon/icon.stories.tsx","tags":["story"],"kind":"Components/Icon","story":"basic","parameters":{"__id":"components-icon--basic","docsOnly":false,"fileName":"./src/icon/icon.stories.tsx"}},"components-icon--in-text":{"id":"components-icon--in-text","name":"in text","title":"Components/Icon","importPath":"./src/icon/icon.stories.tsx","tags":["story"],"kind":"Components/Icon","story":"in text","parameters":{"__id":"components-icon--in-text","docsOnly":false,"fileName":"./src/icon/icon.stories.tsx"}},"components-icon--all-icons-list":{"id":"components-icon--all-icons-list","name":"all icons list","title":"Components/Icon","importPath":"./src/icon/icon.stories.tsx","tags":["story"],"kind":"Components/Icon","story":"all icons list","parameters":{"__id":"components-icon--all-icons-list","docsOnly":false,"fileName":"./src/icon/icon.stories.tsx"}},"components-icon--jet-brains-product-logos-list":{"id":"components-icon--jet-brains-product-logos-list","name":"JetBrains product logos list","title":"Components/Icon","importPath":"./src/icon/icon.stories.tsx","tags":["story"],"kind":"Components/Icon","story":"JetBrains product logos list","parameters":{"__id":"components-icon--jet-brains-product-logos-list","docsOnly":false,"fileName":"./src/icon/icon.stories.tsx"}},"style-only-input-sizes--basic":{"id":"style-only-input-sizes--basic","name":"Input Sizes","title":"Style-only/Input Sizes","importPath":"./src/input-size/input-size.stories.js","tags":["story"],"kind":"Style-only/Input Sizes","story":"Input Sizes","parameters":{"__id":"style-only-input-sizes--basic","docsOnly":false,"fileName":"./src/input-size/input-size.stories.js"}},"components-input--basic":{"id":"components-input--basic","name":"basic","title":"Components/Input","importPath":"./src/input/input.stories.tsx","tags":["story"],"kind":"Components/Input","story":"basic","parameters":{"__id":"components-input--basic","docsOnly":false,"fileName":"./src/input/input.stories.tsx"}},"components-input--height-s":{"id":"components-input--height-s","name":"Height S","title":"Components/Input","importPath":"./src/input/input.stories.tsx","tags":["story"],"kind":"Components/Input","story":"Height S","parameters":{"__id":"components-input--height-s","docsOnly":false,"fileName":"./src/input/input.stories.tsx"}},"components-input--select-all":{"id":"components-input--select-all","name":"Select All","title":"Components/Input","importPath":"./src/input/input.stories.tsx","tags":["story"],"kind":"Components/Input","story":"Select All","parameters":{"__id":"components-input--select-all","docsOnly":false,"fileName":"./src/input/input.stories.tsx"}},"style-only-island--basic":{"id":"style-only-island--basic","name":"basic","title":"Style-only/Island","importPath":"./src/island-legacy/island-legacy.stories.tsx","tags":["story"],"kind":"Style-only/Island","story":"basic","parameters":{"__id":"style-only-island--basic","docsOnly":false,"fileName":"./src/island-legacy/island-legacy.stories.tsx"}},"style-only-island--with-a-header-and-buttons":{"id":"style-only-island--with-a-header-and-buttons","name":"with a header and buttons","title":"Style-only/Island","importPath":"./src/island-legacy/island-legacy.stories.tsx","tags":["story"],"kind":"Style-only/Island","story":"with a header and buttons","parameters":{"__id":"style-only-island--with-a-header-and-buttons","docsOnly":false,"fileName":"./src/island-legacy/island-legacy.stories.tsx"}},"components-island--basic":{"id":"components-island--basic","name":"basic","title":"Components/Island","importPath":"./src/island/island.stories.tsx","tags":["story"],"kind":"Components/Island","story":"basic","parameters":{"__id":"components-island--basic","docsOnly":false,"fileName":"./src/island/island.stories.tsx"}},"components-island--with-scroll":{"id":"components-island--with-scroll","name":"with scroll","title":"Components/Island","importPath":"./src/island/island.stories.tsx","tags":["story"],"kind":"Components/Island","story":"with scroll","parameters":{"__id":"components-island--with-scroll","docsOnly":false,"fileName":"./src/island/island.stories.tsx"}},"components-island--with-resizeable-header":{"id":"components-island--with-resizeable-header","name":"with resizeable header","title":"Components/Island","importPath":"./src/island/island.stories.tsx","tags":["story"],"kind":"Components/Island","story":"with resizeable header","parameters":{"__id":"components-island--with-resizeable-header","docsOnly":false,"fileName":"./src/island/island.stories.tsx"}},"components-link--all-variants":{"id":"components-link--all-variants","name":"Link","title":"Components/Link","importPath":"./src/link/link.stories.tsx","tags":["story"],"kind":"Components/Link","story":"Link","parameters":{"__id":"components-link--all-variants","docsOnly":false,"fileName":"./src/link/link.stories.tsx"}},"components-list--basic":{"id":"components-list--basic","name":"basic","title":"Components/List","importPath":"./src/list/list.stories.tsx","tags":["story"],"kind":"Components/List","story":"basic","parameters":{"__id":"components-list--basic","docsOnly":false,"fileName":"./src/list/list.stories.tsx"}},"components-list--with-a-hint-below":{"id":"components-list--with-a-hint-below","name":"with a hint below","title":"Components/List","importPath":"./src/list/list.stories.tsx","tags":["story"],"kind":"Components/List","story":"with a hint below","parameters":{"__id":"components-list--with-a-hint-below","docsOnly":false,"fileName":"./src/list/list.stories.tsx"}},"components-list--long-list":{"id":"components-list--long-list","name":"long list","title":"Components/List","importPath":"./src/list/list.stories.tsx","tags":["story"],"kind":"Components/List","story":"long list","parameters":{"__id":"components-list--long-list","docsOnly":false,"fileName":"./src/list/list.stories.tsx"}},"components-list--list-2":{"id":"components-list--list-2","name":"list #2","title":"Components/List","importPath":"./src/list/list.stories.tsx","tags":["story"],"kind":"Components/List","story":"list #2","parameters":{"__id":"components-list--list-2","docsOnly":false,"fileName":"./src/list/list.stories.tsx"}},"components-list--with-item-icons":{"id":"components-list--with-item-icons","name":"with item icons","title":"Components/List","importPath":"./src/list/list.stories.tsx","tags":["story"],"kind":"Components/List","story":"with item icons","parameters":{"__id":"components-list--with-item-icons","docsOnly":false,"fileName":"./src/list/list.stories.tsx"}},"components-list--with-deprecated-item-type-parameter":{"id":"components-list--with-deprecated-item-type-parameter","name":"with deprecated item.type parameter","title":"Components/List","importPath":"./src/list/list.stories.tsx","tags":["story"],"kind":"Components/List","story":"with deprecated item.type parameter","parameters":{"__id":"components-list--with-deprecated-item-type-parameter","docsOnly":false,"fileName":"./src/list/list.stories.tsx"}},"components-list--with-custom-items":{"id":"components-list--with-custom-items","name":"with custom items","title":"Components/List","importPath":"./src/list/list.stories.tsx","tags":["story"],"kind":"Components/List","story":"with custom items","parameters":{"__id":"components-list--with-custom-items","docsOnly":false,"fileName":"./src/list/list.stories.tsx"}},"components-list--with-users":{"id":"components-list--with-users","name":"with users","title":"Components/List","importPath":"./src/list/list.stories.tsx","tags":["story"],"kind":"Components/List","story":"with users","parameters":{"__id":"components-list--with-users","docsOnly":false,"fileName":"./src/list/list.stories.tsx"}},"components-list--with-custom-tooltip":{"id":"components-list--with-custom-tooltip","name":"with custom tooltip","title":"Components/List","importPath":"./src/list/list.stories.tsx","tags":["story"],"kind":"Components/List","story":"with custom tooltip","parameters":{"__id":"components-list--with-custom-tooltip","docsOnly":false,"fileName":"./src/list/list.stories.tsx"}},"components-inline-loader--basic":{"id":"components-inline-loader--basic","name":"basic","title":"Components/Inline Loader","importPath":"./src/loader-inline/loader-inline.stories.tsx","tags":["story"],"kind":"Components/Inline Loader","story":"basic","parameters":{"__id":"components-inline-loader--basic","docsOnly":false,"fileName":"./src/loader-inline/loader-inline.stories.tsx"}},"components-inline-loader--with-children":{"id":"components-inline-loader--with-children","name":"with children","title":"Components/Inline Loader","importPath":"./src/loader-inline/loader-inline.stories.tsx","tags":["story"],"kind":"Components/Inline Loader","story":"with children","parameters":{"__id":"components-inline-loader--with-children","docsOnly":false,"fileName":"./src/loader-inline/loader-inline.stories.tsx"}},"components-inline-loader--on-custom-background":{"id":"components-inline-loader--on-custom-background","name":"on custom background","title":"Components/Inline Loader","importPath":"./src/loader-inline/loader-inline.stories.tsx","tags":["story"],"kind":"Components/Inline Loader","story":"on custom background","parameters":{"__id":"components-inline-loader--on-custom-background","docsOnly":false,"fileName":"./src/loader-inline/loader-inline.stories.tsx"}},"components-inline-loader--without-react":{"id":"components-inline-loader--without-react","name":"without React","title":"Components/Inline Loader","importPath":"./src/loader-inline/loader-inline.stories.tsx","tags":["story"],"kind":"Components/Inline Loader","story":"without React","parameters":{"__id":"components-inline-loader--without-react","docsOnly":false,"fileName":"./src/loader-inline/loader-inline.stories.tsx"}},"components-loader-screen--basic":{"id":"components-loader-screen--basic","name":"basic","title":"Components/Loader Screen","importPath":"./src/loader-screen/loader-screen.stories.tsx","tags":["story"],"kind":"Components/Loader Screen","story":"basic","parameters":{"__id":"components-loader-screen--basic","docsOnly":false,"fileName":"./src/loader-screen/loader-screen.stories.tsx"}},"components-loader-screen--with-message":{"id":"components-loader-screen--with-message","name":"with message","title":"Components/Loader Screen","importPath":"./src/loader-screen/loader-screen.stories.tsx","tags":["story"],"kind":"Components/Loader Screen","story":"with message","parameters":{"__id":"components-loader-screen--with-message","docsOnly":false,"fileName":"./src/loader-screen/loader-screen.stories.tsx"}},"components-loader--basic":{"id":"components-loader--basic","name":"Loader","title":"Components/Loader","importPath":"./src/loader/loader.stories.tsx","tags":["story"],"kind":"Components/Loader","story":"Loader","parameters":{"__id":"components-loader--basic","docsOnly":false,"fileName":"./src/loader/loader.stories.tsx"}},"components-markdown--basic":{"id":"components-markdown--basic","name":"basic","title":"Components/Markdown","importPath":"./src/markdown/markdown.stories.tsx","tags":["story"],"kind":"Components/Markdown","story":"basic","parameters":{"__id":"components-markdown--basic","docsOnly":false,"fileName":"./src/markdown/markdown.stories.tsx"}},"components-message--basic":{"id":"components-message--basic","name":"basic","title":"Components/Message","importPath":"./src/message/message.stories.tsx","tags":["story"],"kind":"Components/Message","story":"basic","parameters":{"__id":"components-message--basic","docsOnly":false,"fileName":"./src/message/message.stories.tsx"}},"components-message--light":{"id":"components-message--light","name":"Light","title":"Components/Message","importPath":"./src/message/message.stories.tsx","tags":["story"],"kind":"Components/Message","story":"Light","parameters":{"__id":"components-message--light","docsOnly":false,"fileName":"./src/message/message.stories.tsx"}},"components-message--with-on-dissmiss":{"id":"components-message--with-on-dissmiss","name":"with onDissmiss","title":"Components/Message","importPath":"./src/message/message.stories.tsx","tags":["story"],"kind":"Components/Message","story":"with onDissmiss","parameters":{"__id":"components-message--with-on-dissmiss","docsOnly":false,"fileName":"./src/message/message.stories.tsx"}},"components-message--wish-narrow-anchor":{"id":"components-message--wish-narrow-anchor","name":"with narrow anchor","title":"Components/Message","importPath":"./src/message/message.stories.tsx","tags":["story"],"kind":"Components/Message","story":"with narrow anchor","parameters":{"__id":"components-message--wish-narrow-anchor","docsOnly":false,"fileName":"./src/message/message.stories.tsx"}},"style-only-old-browsers-message--basic":{"id":"style-only-old-browsers-message--basic","name":"Old Browsers Message","title":"Style-only/Old Browsers Message","importPath":"./src/old-browsers-message/old-browsers-message.stories.tsx","tags":["story"],"kind":"Style-only/Old Browsers Message","story":"Old Browsers Message","parameters":{"__id":"style-only-old-browsers-message--basic","docsOnly":false,"fileName":"./src/old-browsers-message/old-browsers-message.stories.tsx"}},"components-pager--basic":{"id":"components-pager--basic","name":"basic","title":"Components/Pager","importPath":"./src/pager/pager.stories.tsx","tags":["story"],"kind":"Components/Pager","story":"basic","parameters":{"__id":"components-pager--basic","docsOnly":false,"fileName":"./src/pager/pager.stories.tsx"}},"components-pager--custom-frame-size":{"id":"components-pager--custom-frame-size","name":"custom frame size","title":"Components/Pager","importPath":"./src/pager/pager.stories.tsx","tags":["story"],"kind":"Components/Pager","story":"custom frame size","parameters":{"__id":"components-pager--custom-frame-size","docsOnly":false,"fileName":"./src/pager/pager.stories.tsx"}},"components-pager--custom-frame-size-2":{"id":"components-pager--custom-frame-size-2","name":"custom frame size #2","title":"Components/Pager","importPath":"./src/pager/pager.stories.tsx","tags":["story"],"kind":"Components/Pager","story":"custom frame size #2","parameters":{"__id":"components-pager--custom-frame-size-2","docsOnly":false,"fileName":"./src/pager/pager.stories.tsx"}},"components-pager--custom-frame-size-3":{"id":"components-pager--custom-frame-size-3","name":"custom frame size #3","title":"Components/Pager","importPath":"./src/pager/pager.stories.tsx","tags":["story"],"kind":"Components/Pager","story":"custom frame size #3","parameters":{"__id":"components-pager--custom-frame-size-3","docsOnly":false,"fileName":"./src/pager/pager.stories.tsx"}},"components-pager--page-size-selector":{"id":"components-pager--page-size-selector","name":"page size selector","title":"Components/Pager","importPath":"./src/pager/pager.stories.tsx","tags":["story"],"kind":"Components/Pager","story":"page size selector","parameters":{"__id":"components-pager--page-size-selector","docsOnly":false,"fileName":"./src/pager/pager.stories.tsx"}},"components-pager--open-total":{"id":"components-pager--open-total","name":"open total","title":"Components/Pager","importPath":"./src/pager/pager.stories.tsx","tags":["story"],"kind":"Components/Pager","story":"open total","parameters":{"__id":"components-pager--open-total","docsOnly":false,"fileName":"./src/pager/pager.stories.tsx"}},"components-pager--open-total-and-history-support":{"id":"components-pager--open-total-and-history-support","name":"open total and history support","title":"Components/Pager","importPath":"./src/pager/pager.stories.tsx","tags":["story"],"kind":"Components/Pager","story":"open total and history support","parameters":{"__id":"components-pager--open-total-and-history-support","docsOnly":false,"fileName":"./src/pager/pager.stories.tsx"}},"components-pager--reload-on-current-page-change":{"id":"components-pager--reload-on-current-page-change","name":"reload on current page change","title":"Components/Pager","importPath":"./src/pager/pager.stories.tsx","tags":["story"],"kind":"Components/Pager","story":"reload on current page change","parameters":{"__id":"components-pager--reload-on-current-page-change","docsOnly":false,"fileName":"./src/pager/pager.stories.tsx"}},"components-panel--basic":{"id":"components-panel--basic","name":"Panel","title":"Components/Panel","importPath":"./src/panel/panel.stories.tsx","tags":["story"],"kind":"Components/Panel","story":"Panel","parameters":{"__id":"components-panel--basic","docsOnly":false,"fileName":"./src/panel/panel.stories.tsx"}},"components-popupmenu--basic":{"id":"components-popupmenu--basic","name":"PopupMenu","title":"Components/PopupMenu","importPath":"./src/popup-menu/popup-menu.stories.tsx","tags":["story"],"kind":"Components/PopupMenu","story":"PopupMenu","parameters":{"__id":"components-popupmenu--basic","docsOnly":false,"fileName":"./src/popup-menu/popup-menu.stories.tsx"}},"components-popup--basic":{"id":"components-popup--basic","name":"basic","title":"Components/Popup","importPath":"./src/popup/popup.stories.tsx","tags":["story"],"kind":"Components/Popup","story":"basic","parameters":{"__id":"components-popup--basic","docsOnly":false,"fileName":"./src/popup/popup.stories.tsx"}},"components-popup--auto-positioning":{"id":"components-popup--auto-positioning","name":"auto-positioning","title":"Components/Popup","importPath":"./src/popup/popup.stories.tsx","tags":["story"],"kind":"Components/Popup","story":"auto-positioning","parameters":{"__id":"components-popup--auto-positioning","docsOnly":false,"fileName":"./src/popup/popup.stories.tsx"}},"components-popup--popup-in-a-popup":{"id":"components-popup--popup-in-a-popup","name":"popup in a popup","title":"Components/Popup","importPath":"./src/popup/popup.stories.tsx","tags":["story"],"kind":"Components/Popup","story":"popup in a popup","parameters":{"__id":"components-popup--popup-in-a-popup","docsOnly":false,"fileName":"./src/popup/popup.stories.tsx"}},"components-popup--inside-a-scrollable-container":{"id":"components-popup--inside-a-scrollable-container","name":"inside a scrollable container","title":"Components/Popup","importPath":"./src/popup/popup.stories.tsx","tags":["story"],"kind":"Components/Popup","story":"inside a scrollable container","parameters":{"__id":"components-popup--inside-a-scrollable-container","docsOnly":false,"fileName":"./src/popup/popup.stories.tsx"}},"components-popup--fits-screen":{"id":"components-popup--fits-screen","name":"fits screen","title":"Components/Popup","importPath":"./src/popup/popup.stories.tsx","tags":["story"],"kind":"Components/Popup","story":"fits screen","parameters":{"__id":"components-popup--fits-screen","docsOnly":false,"fileName":"./src/popup/popup.stories.tsx"}},"components-progress-bar--basic":{"id":"components-progress-bar--basic","name":"Progress Bar","title":"Components/Progress Bar","importPath":"./src/progress-bar/progress-bar.stories.tsx","tags":["story"],"kind":"Components/Progress Bar","story":"Progress Bar","parameters":{"__id":"components-progress-bar--basic","docsOnly":false,"fileName":"./src/progress-bar/progress-bar.stories.tsx"}},"components-query-assist--basic":{"id":"components-query-assist--basic","name":"basic","title":"Components/Query Assist","importPath":"./src/query-assist/query-assist.stories.tsx","tags":["story"],"kind":"Components/Query Assist","story":"basic","parameters":{"__id":"components-query-assist--basic","docsOnly":false,"fileName":"./src/query-assist/query-assist.stories.tsx"}},"components-query-assist--no-auth":{"id":"components-query-assist--no-auth","name":"no auth","title":"Components/Query Assist","importPath":"./src/query-assist/query-assist.stories.tsx","tags":["story"],"kind":"Components/Query Assist","story":"no auth","parameters":{"__id":"components-query-assist--no-auth","docsOnly":false,"fileName":"./src/query-assist/query-assist.stories.tsx"}},"components-query-assist--with-custom-renderer":{"id":"components-query-assist--with-custom-renderer","name":"with custom renderer","title":"Components/Query Assist","importPath":"./src/query-assist/query-assist.stories.tsx","tags":["story"],"kind":"Components/Query Assist","story":"with custom renderer","parameters":{"__id":"components-query-assist--with-custom-renderer","docsOnly":false,"fileName":"./src/query-assist/query-assist.stories.tsx"}},"components-query-assist--with-custom-actions":{"id":"components-query-assist--with-custom-actions","name":"with custom actions","title":"Components/Query Assist","importPath":"./src/query-assist/query-assist.stories.tsx","tags":["story"],"kind":"Components/Query Assist","story":"with custom actions","parameters":{"__id":"components-query-assist--with-custom-actions","docsOnly":false,"fileName":"./src/query-assist/query-assist.stories.tsx"}},"components-query-assist--huge-one":{"id":"components-query-assist--huge-one","name":"huge one","title":"Components/Query Assist","importPath":"./src/query-assist/query-assist.stories.tsx","tags":["story"],"kind":"Components/Query Assist","story":"huge one","parameters":{"__id":"components-query-assist--huge-one","docsOnly":false,"fileName":"./src/query-assist/query-assist.stories.tsx"}},"components-query-assist--disabled-one":{"id":"components-query-assist--disabled-one","name":"disabled one","title":"Components/Query Assist","importPath":"./src/query-assist/query-assist.stories.tsx","tags":["story"],"kind":"Components/Query Assist","story":"disabled one","parameters":{"__id":"components-query-assist--disabled-one","docsOnly":false,"fileName":"./src/query-assist/query-assist.stories.tsx"}},"components-radio--basic":{"id":"components-radio--basic","name":"basic","title":"Components/Radio","importPath":"./src/radio/radio.stories.tsx","tags":["story"],"kind":"Components/Radio","story":"basic","parameters":{"__id":"components-radio--basic","docsOnly":false,"fileName":"./src/radio/radio.stories.tsx"}},"components-radio--multiline":{"id":"components-radio--multiline","name":"multiline","title":"Components/Radio","importPath":"./src/radio/radio.stories.tsx","tags":["story"],"kind":"Components/Radio","story":"multiline","parameters":{"__id":"components-radio--multiline","docsOnly":false,"fileName":"./src/radio/radio.stories.tsx"}},"components-radio--uncontrolled":{"id":"components-radio--uncontrolled","name":"uncontrolled","title":"Components/Radio","importPath":"./src/radio/radio.stories.tsx","tags":["story"],"kind":"Components/Radio","story":"uncontrolled","parameters":{"__id":"components-radio--uncontrolled","docsOnly":false,"fileName":"./src/radio/radio.stories.tsx"}},"components-radio--disabled":{"id":"components-radio--disabled","name":"disabled","title":"Components/Radio","importPath":"./src/radio/radio.stories.tsx","tags":["story"],"kind":"Components/Radio","story":"disabled","parameters":{"__id":"components-radio--disabled","docsOnly":false,"fileName":"./src/radio/radio.stories.tsx"}},"components-select--with-a-filter-and-tags":{"id":"components-select--with-a-filter-and-tags","name":"with a filter and tags","title":"Components/Select","importPath":"./src/select/select.stories.tsx","tags":["story"],"kind":"Components/Select","story":"with a filter and tags","parameters":{"__id":"components-select--with-a-filter-and-tags","docsOnly":false,"fileName":"./src/select/select.stories.tsx"}},"components-select--with-avatars":{"id":"components-select--with-avatars","name":"With Avatars","title":"Components/Select","importPath":"./src/select/select.stories.tsx","tags":["story"],"kind":"Components/Select","story":"With Avatars","parameters":{"__id":"components-select--with-avatars","docsOnly":false,"fileName":"./src/select/select.stories.tsx"}},"components-select--with-a-filter":{"id":"components-select--with-a-filter","name":"with a filter","title":"Components/Select","importPath":"./src/select/select.stories.tsx","tags":["story"],"kind":"Components/Select","story":"with a filter","parameters":{"__id":"components-select--with-a-filter","docsOnly":false,"fileName":"./src/select/select.stories.tsx"}},"components-select--button-mode-with-a-filter":{"id":"components-select--button-mode-with-a-filter","name":"button mode with a filter","title":"Components/Select","importPath":"./src/select/select.stories.tsx","tags":["story"],"kind":"Components/Select","story":"button mode with a filter","parameters":{"__id":"components-select--button-mode-with-a-filter","docsOnly":false,"fileName":"./src/select/select.stories.tsx"}},"components-select--inline-with-a-filter":{"id":"components-select--inline-with-a-filter","name":"inline with a filter","title":"Components/Select","importPath":"./src/select/select.stories.tsx","tags":["story"],"kind":"Components/Select","story":"inline with a filter","parameters":{"__id":"components-select--inline-with-a-filter","docsOnly":false,"fileName":"./src/select/select.stories.tsx"}},"components-select--inline-opens-to-left":{"id":"components-select--inline-opens-to-left","name":"inline (opens to left)","title":"Components/Select","importPath":"./src/select/select.stories.tsx","tags":["story"],"kind":"Components/Select","story":"inline (opens to left)","parameters":{"__id":"components-select--inline-opens-to-left","docsOnly":false,"fileName":"./src/select/select.stories.tsx"}},"components-select--with-disabled-move-overflow":{"id":"components-select--with-disabled-move-overflow","name":"with disabled move overflow","title":"Components/Select","importPath":"./src/select/select.stories.tsx","tags":["story"],"kind":"Components/Select","story":"with disabled move overflow","parameters":{"__id":"components-select--with-disabled-move-overflow","docsOnly":false,"fileName":"./src/select/select.stories.tsx"}},"components-select--with-server-side-filtering":{"id":"components-select--with-server-side-filtering","name":"with server-side filtering","title":"Components/Select","importPath":"./src/select/select.stories.tsx","tags":["story"],"kind":"Components/Select","story":"with server-side filtering","parameters":{"__id":"components-select--with-server-side-filtering","docsOnly":false,"fileName":"./src/select/select.stories.tsx"}},"components-select--with-fuzzy-search-filter":{"id":"components-select--with-fuzzy-search-filter","name":"with fuzzy search filter","title":"Components/Select","importPath":"./src/select/select.stories.tsx","tags":["story"],"kind":"Components/Select","story":"with fuzzy search filter","parameters":{"__id":"components-select--with-fuzzy-search-filter","docsOnly":false,"fileName":"./src/select/select.stories.tsx"}},"components-select--with-a-large-dataset":{"id":"components-select--with-a-large-dataset","name":"with a large dataset","title":"Components/Select","importPath":"./src/select/select.stories.tsx","tags":["story"],"kind":"Components/Select","story":"with a large dataset","parameters":{"__id":"components-select--with-a-large-dataset","docsOnly":false,"fileName":"./src/select/select.stories.tsx"}},"components-select--with-a-large-dataset-and-disabled-scroll-to-active-item":{"id":"components-select--with-a-large-dataset-and-disabled-scroll-to-active-item","name":"with a large dataset and disabled scroll to active item","title":"Components/Select","importPath":"./src/select/select.stories.tsx","tags":["story"],"kind":"Components/Select","story":"with a large dataset and disabled scroll to active item","parameters":{"__id":"components-select--with-a-large-dataset-and-disabled-scroll-to-active-item","docsOnly":false,"fileName":"./src/select/select.stories.tsx"}},"components-select--multiple-with-a-description":{"id":"components-select--multiple-with-a-description","name":"multiple with a description","title":"Components/Select","importPath":"./src/select/select.stories.tsx","tags":["story"],"kind":"Components/Select","story":"multiple with a description","parameters":{"__id":"components-select--multiple-with-a-description","docsOnly":false,"fileName":"./src/select/select.stories.tsx"}},"components-select--disabled":{"id":"components-select--disabled","name":"disabled","title":"Components/Select","importPath":"./src/select/select.stories.tsx","tags":["story"],"kind":"Components/Select","story":"disabled","parameters":{"__id":"components-select--disabled","docsOnly":false,"fileName":"./src/select/select.stories.tsx"}},"components-select--input-based":{"id":"components-select--input-based","name":"input-based","title":"Components/Select","importPath":"./src/select/select.stories.tsx","tags":["story"],"kind":"Components/Select","story":"input-based","parameters":{"__id":"components-select--input-based","docsOnly":false,"fileName":"./src/select/select.stories.tsx"}},"components-select--input-based-in-suggest-only-mode":{"id":"components-select--input-based-in-suggest-only-mode","name":"input-based in suggest-only mode","title":"Components/Select","importPath":"./src/select/select.stories.tsx","tags":["story"],"kind":"Components/Select","story":"input-based in suggest-only mode","parameters":{"__id":"components-select--input-based-in-suggest-only-mode","docsOnly":false,"fileName":"./src/select/select.stories.tsx"}},"components-select--input-based-with-error":{"id":"components-select--input-based-with-error","name":"input-based with error","title":"Components/Select","importPath":"./src/select/select.stories.tsx","tags":["story"],"kind":"Components/Select","story":"input-based with error","parameters":{"__id":"components-select--input-based-with-error","docsOnly":false,"fileName":"./src/select/select.stories.tsx"}},"components-select--input-based-with-filter-icon":{"id":"components-select--input-based-with-filter-icon","name":"input-based with filter icon","title":"Components/Select","importPath":"./src/select/select.stories.tsx","tags":["story"],"kind":"Components/Select","story":"input-based with filter icon","parameters":{"__id":"components-select--input-based-with-filter-icon","docsOnly":false,"fileName":"./src/select/select.stories.tsx"}},"components-select--with-sub-levels-for-list-element":{"id":"components-select--with-sub-levels-for-list-element","name":"with sub levels for list element","title":"Components/Select","importPath":"./src/select/select.stories.tsx","tags":["story"],"kind":"Components/Select","story":"with sub levels for list element","parameters":{"__id":"components-select--with-sub-levels-for-list-element","docsOnly":false,"fileName":"./src/select/select.stories.tsx"}},"components-select--with-default-filter-mode-and-a-loading-indicator":{"id":"components-select--with-default-filter-mode-and-a-loading-indicator","name":"with default filter mode and a loading indicator","title":"Components/Select","importPath":"./src/select/select.stories.tsx","tags":["story"],"kind":"Components/Select","story":"with default filter mode and a loading indicator","parameters":{"__id":"components-select--with-default-filter-mode-and-a-loading-indicator","docsOnly":false,"fileName":"./src/select/select.stories.tsx"}},"components-select--with-a-customized-filter-and-an-add-item-button":{"id":"components-select--with-a-customized-filter-and-an-add-item-button","name":"with a customized filter and an 'Add item' button","title":"Components/Select","importPath":"./src/select/select.stories.tsx","tags":["story"],"kind":"Components/Select","story":"with a customized filter and an 'Add item' button","parameters":{"__id":"components-select--with-a-customized-filter-and-an-add-item-button","docsOnly":false,"fileName":"./src/select/select.stories.tsx"}},"components-select--with-custom-items-and-an-add-item-button":{"id":"components-select--with-custom-items-and-an-add-item-button","name":"with custom items and an 'Add item' button","title":"Components/Select","importPath":"./src/select/select.stories.tsx","tags":["story"],"kind":"Components/Select","story":"with custom items and an 'Add item' button","parameters":{"__id":"components-select--with-custom-items-and-an-add-item-button","docsOnly":false,"fileName":"./src/select/select.stories.tsx"}},"components-select--with-an-always-visible-add-item-button":{"id":"components-select--with-an-always-visible-add-item-button","name":"with an always visible 'Add item' button","title":"Components/Select","importPath":"./src/select/select.stories.tsx","tags":["story"],"kind":"Components/Select","story":"with an always visible 'Add item' button","parameters":{"__id":"components-select--with-an-always-visible-add-item-button","docsOnly":false,"fileName":"./src/select/select.stories.tsx"}},"components-select--multiple-with-custom-view":{"id":"components-select--multiple-with-custom-view","name":"multiple with custom view","title":"Components/Select","importPath":"./src/select/select.stories.tsx","tags":["story"],"kind":"Components/Select","story":"multiple with custom view","parameters":{"__id":"components-select--multiple-with-custom-view","docsOnly":false,"fileName":"./src/select/select.stories.tsx"}},"components-select--as-a-dropdown-without-filter":{"id":"components-select--as-a-dropdown-without-filter","name":"as a dropdown without filter","title":"Components/Select","importPath":"./src/select/select.stories.tsx","tags":["story"],"kind":"Components/Select","story":"as a dropdown without filter","parameters":{"__id":"components-select--as-a-dropdown-without-filter","docsOnly":false,"fileName":"./src/select/select.stories.tsx"}},"components-select--with-custom-input-anchor":{"id":"components-select--with-custom-input-anchor","name":"with custom input anchor","title":"Components/Select","importPath":"./src/select/select.stories.tsx","tags":["story"],"kind":"Components/Select","story":"with custom input anchor","parameters":{"__id":"components-select--with-custom-input-anchor","docsOnly":false,"fileName":"./src/select/select.stories.tsx"}},"components-select--with-render-optimization":{"id":"components-select--with-render-optimization","name":"with render optimization","title":"Components/Select","importPath":"./src/select/select.stories.tsx","tags":["story"],"kind":"Components/Select","story":"with render optimization","parameters":{"__id":"components-select--with-render-optimization","docsOnly":false,"fileName":"./src/select/select.stories.tsx"}},"components-select--fits-to-screen":{"id":"components-select--fits-to-screen","name":"fits to screen","title":"Components/Select","importPath":"./src/select/select.stories.tsx","tags":["story"],"kind":"Components/Select","story":"fits to screen","parameters":{"__id":"components-select--fits-to-screen","docsOnly":false,"fileName":"./src/select/select.stories.tsx"}},"components-select--with-filtered-fields":{"id":"components-select--with-filtered-fields","name":"with filtered fields","title":"Components/Select","importPath":"./src/select/select.stories.tsx","tags":["story"],"kind":"Components/Select","story":"with filtered fields","parameters":{"__id":"components-select--with-filtered-fields","docsOnly":false,"fileName":"./src/select/select.stories.tsx"}},"components-select--multiple-with-select-all":{"id":"components-select--multiple-with-select-all","name":"multiple with select all","title":"Components/Select","importPath":"./src/select/select.stories.tsx","tags":["story"],"kind":"Components/Select","story":"multiple with select all","parameters":{"__id":"components-select--multiple-with-select-all","docsOnly":false,"fileName":"./src/select/select.stories.tsx"}},"components-select--multiple-with-select-all-and-disabled-item":{"id":"components-select--multiple-with-select-all-and-disabled-item","name":"multiple with select all and disabled item","title":"Components/Select","importPath":"./src/select/select.stories.tsx","tags":["story"],"kind":"Components/Select","story":"multiple with select all and disabled item","parameters":{"__id":"components-select--multiple-with-select-all-and-disabled-item","docsOnly":false,"fileName":"./src/select/select.stories.tsx"}},"components-select--multiple-with-select-all-and-custom-labels":{"id":"components-select--multiple-with-select-all-and-custom-labels","name":"multiple with select all and custom labels","title":"Components/Select","importPath":"./src/select/select.stories.tsx","tags":["story"],"kind":"Components/Select","story":"multiple with select all and custom labels","parameters":{"__id":"components-select--multiple-with-select-all-and-custom-labels","docsOnly":false,"fileName":"./src/select/select.stories.tsx"}},"components-select--multiple-with-limit":{"id":"components-select--multiple-with-limit","name":"multiple with limit","title":"Components/Select","importPath":"./src/select/select.stories.tsx","tags":["story"],"kind":"Components/Select","story":"multiple with limit","parameters":{"__id":"components-select--multiple-with-limit","docsOnly":false,"fileName":"./src/select/select.stories.tsx"}},"components-select--select-in-popup":{"id":"components-select--select-in-popup","name":"Select in Popup","title":"Components/Select","importPath":"./src/select/select.stories.tsx","tags":["story"],"kind":"Components/Select","story":"Select in Popup","parameters":{"__id":"components-select--select-in-popup","docsOnly":false,"fileName":"./src/select/select.stories.tsx"}},"components-select--height-s":{"id":"components-select--height-s","name":"Height S","title":"Components/Select","importPath":"./src/select/select.stories.tsx","tags":["story"],"kind":"Components/Select","story":"Height S","parameters":{"__id":"components-select--height-s","docsOnly":false,"fileName":"./src/select/select.stories.tsx"}},"components-storage--basic":{"id":"components-storage--basic","name":"Storage","title":"Components/Storage","importPath":"./src/storage/storage.stories.tsx","tags":["story"],"kind":"Components/Storage","story":"Storage","parameters":{"__id":"components-storage--basic","docsOnly":false,"fileName":"./src/storage/storage.stories.tsx"}},"components-tabtrap--basic":{"id":"components-tabtrap--basic","name":"TabTrap","title":"Components/TabTrap","importPath":"./src/tab-trap/tab-trap.stories.tsx","tags":["story"],"kind":"Components/TabTrap","story":"TabTrap","parameters":{"__id":"components-tabtrap--basic","docsOnly":false,"fileName":"./src/tab-trap/tab-trap.stories.tsx"}},"components-table--basic":{"id":"components-table--basic","name":"basic","title":"Components/Table","importPath":"./src/table/table.stories.tsx","tags":["story"],"kind":"Components/Table","story":"basic","parameters":{"__id":"components-table--basic","docsOnly":false,"fileName":"./src/table/table.stories.tsx"}},"components-table--multi-table":{"id":"components-table--multi-table","name":"multi table","title":"Components/Table","importPath":"./src/table/table.stories.tsx","tags":["story"],"kind":"Components/Table","story":"multi table","parameters":{"__id":"components-table--multi-table","docsOnly":false,"fileName":"./src/table/table.stories.tsx"}},"components-table--empty-table":{"id":"components-table--empty-table","name":"empty table","title":"Components/Table","importPath":"./src/table/table.stories.tsx","tags":["story"],"kind":"Components/Table","story":"empty table","parameters":{"__id":"components-table--empty-table","docsOnly":false,"fileName":"./src/table/table.stories.tsx"}},"components-tabs--basic":{"id":"components-tabs--basic","name":"basic","title":"Components/Tabs","importPath":"./src/tabs/tabs.stories.tsx","tags":["story"],"kind":"Components/Tabs","story":"basic","parameters":{"__id":"components-tabs--basic","docsOnly":false,"fileName":"./src/tabs/tabs.stories.tsx"}},"components-tabs--auto-collapse-demo":{"id":"components-tabs--auto-collapse-demo","name":"Auto collapsing","title":"Components/Tabs","importPath":"./src/tabs/tabs.stories.tsx","tags":["story"],"kind":"Components/Tabs","story":"Auto collapsing","parameters":{"__id":"components-tabs--auto-collapse-demo","docsOnly":false,"fileName":"./src/tabs/tabs.stories.tsx"}},"components-tabs--smart":{"id":"components-tabs--smart","name":"smart","title":"Components/Tabs","importPath":"./src/tabs/tabs.stories.tsx","tags":["story"],"kind":"Components/Tabs","story":"smart","parameters":{"__id":"components-tabs--smart","docsOnly":false,"fileName":"./src/tabs/tabs.stories.tsx"}},"components-tabs--custom-titles":{"id":"components-tabs--custom-titles","name":"custom titles","title":"Components/Tabs","importPath":"./src/tabs/tabs.stories.tsx","tags":["story"],"kind":"Components/Tabs","story":"custom titles","parameters":{"__id":"components-tabs--custom-titles","docsOnly":false,"fileName":"./src/tabs/tabs.stories.tsx"}},"components-tabs--custom-titles-function":{"id":"components-tabs--custom-titles-function","name":"custom titles (function)","title":"Components/Tabs","importPath":"./src/tabs/tabs.stories.tsx","tags":["story"],"kind":"Components/Tabs","story":"custom titles (function)","parameters":{"__id":"components-tabs--custom-titles-function","docsOnly":false,"fileName":"./src/tabs/tabs.stories.tsx"}},"components-tag--demo":{"id":"components-tag--demo","name":"Tag","title":"Components/Tag","importPath":"./src/tag/tag.stories.tsx","tags":["story"],"kind":"Components/Tag","story":"Tag","parameters":{"__id":"components-tag--demo","docsOnly":false,"fileName":"./src/tag/tag.stories.tsx"}},"components-tags-input--basic":{"id":"components-tags-input--basic","name":"basic","title":"Components/Tags Input","importPath":"./src/tags-input/tag-input.stories.tsx","tags":["story"],"kind":"Components/Tags Input","story":"basic","parameters":{"__id":"components-tags-input--basic","docsOnly":false,"fileName":"./src/tags-input/tag-input.stories.tsx"}},"components-tags-input--with-icons":{"id":"components-tags-input--with-icons","name":"with icons","title":"Components/Tags Input","importPath":"./src/tags-input/tag-input.stories.tsx","tags":["story"],"kind":"Components/Tags Input","story":"with icons","parameters":{"__id":"components-tags-input--with-icons","docsOnly":false,"fileName":"./src/tags-input/tag-input.stories.tsx"}},"components-tags-input--disabled":{"id":"components-tags-input--disabled","name":"disabled","title":"Components/Tags Input","importPath":"./src/tags-input/tag-input.stories.tsx","tags":["story"],"kind":"Components/Tags Input","story":"disabled","parameters":{"__id":"components-tags-input--disabled","docsOnly":false,"fileName":"./src/tags-input/tag-input.stories.tsx"}},"components-tags-input--with-too-long-tag-labels":{"id":"components-tags-input--with-too-long-tag-labels","name":"with too long tag labels","title":"Components/Tags Input","importPath":"./src/tags-input/tag-input.stories.tsx","tags":["story"],"kind":"Components/Tags Input","story":"with too long tag labels","parameters":{"__id":"components-tags-input--with-too-long-tag-labels","docsOnly":false,"fileName":"./src/tags-input/tag-input.stories.tsx"}},"components-tags-input--auto-open":{"id":"components-tags-input--auto-open","name":"Auto Open","title":"Components/Tags Input","importPath":"./src/tags-input/tag-input.stories.tsx","tags":["story"],"kind":"Components/Tags Input","story":"Auto Open","parameters":{"__id":"components-tags-input--auto-open","docsOnly":false,"fileName":"./src/tags-input/tag-input.stories.tsx"}},"components-tags-input--auto-open-in-a-dialog":{"id":"components-tags-input--auto-open-in-a-dialog","name":"Auto Open In A Dialog","title":"Components/Tags Input","importPath":"./src/tags-input/tag-input.stories.tsx","tags":["story"],"kind":"Components/Tags Input","story":"Auto Open In A Dialog","parameters":{"__id":"components-tags-input--auto-open-in-a-dialog","docsOnly":false,"fileName":"./src/tags-input/tag-input.stories.tsx"}},"components-tags-list--basic":{"id":"components-tags-list--basic","name":"basic","title":"Components/Tags List","importPath":"./src/tags-list/tags-list.stories.tsx","tags":["story"],"kind":"Components/Tags List","story":"basic","parameters":{"__id":"components-tags-list--basic","docsOnly":false,"fileName":"./src/tags-list/tags-list.stories.tsx"}},"components-tags-list--with-icons":{"id":"components-tags-list--with-icons","name":"with icons","title":"Components/Tags List","importPath":"./src/tags-list/tags-list.stories.tsx","tags":["story"],"kind":"Components/Tags List","story":"with icons","parameters":{"__id":"components-tags-list--with-icons","docsOnly":false,"fileName":"./src/tags-list/tags-list.stories.tsx"}},"components-tags-list--disabled":{"id":"components-tags-list--disabled","name":"disabled","title":"Components/Tags List","importPath":"./src/tags-list/tags-list.stories.tsx","tags":["story"],"kind":"Components/Tags List","story":"disabled","parameters":{"__id":"components-tags-list--disabled","docsOnly":false,"fileName":"./src/tags-list/tags-list.stories.tsx"}},"components-text--basic":{"id":"components-text--basic","name":"Text","title":"Components/Text","importPath":"./src/text/text.stories.tsx","tags":["story"],"kind":"Components/Text","story":"Text","parameters":{"__id":"components-text--basic","docsOnly":false,"fileName":"./src/text/text.stories.tsx"}},"components-toggle--basic":{"id":"components-toggle--basic","name":"Toggle","title":"Components/Toggle","importPath":"./src/toggle/toggle.stories.tsx","tags":["story"],"kind":"Components/Toggle","story":"Toggle","parameters":{"__id":"components-toggle--basic","docsOnly":false,"fileName":"./src/toggle/toggle.stories.tsx"}},"components-tooltip--basic":{"id":"components-tooltip--basic","name":"basic","title":"Components/Tooltip","importPath":"./src/tooltip/tooltip.stories.tsx","tags":["story"],"kind":"Components/Tooltip","story":"basic","parameters":{"__id":"components-tooltip--basic","docsOnly":false,"fileName":"./src/tooltip/tooltip.stories.tsx"}},"components-tooltip--displayed-when-necessary":{"id":"components-tooltip--displayed-when-necessary","name":"displayed when necessary","title":"Components/Tooltip","importPath":"./src/tooltip/tooltip.stories.tsx","tags":["story"],"kind":"Components/Tooltip","story":"displayed when necessary","parameters":{"__id":"components-tooltip--displayed-when-necessary","docsOnly":false,"fileName":"./src/tooltip/tooltip.stories.tsx"}},"components-tooltip--nested":{"id":"components-tooltip--nested","name":"nested","title":"Components/Tooltip","importPath":"./src/tooltip/tooltip.stories.tsx","tags":["story"],"kind":"Components/Tooltip","story":"nested","parameters":{"__id":"components-tooltip--nested","docsOnly":false,"fileName":"./src/tooltip/tooltip.stories.tsx"}},"components-user-agreement--dialog":{"id":"components-user-agreement--dialog","name":"dialog","title":"Components/User Agreement","importPath":"./src/user-agreement/user-agreement.stories.tsx","tags":["story"],"kind":"Components/User Agreement","story":"dialog","parameters":{"__id":"components-user-agreement--dialog","docsOnly":false,"fileName":"./src/user-agreement/user-agreement.stories.tsx"}},"components-user-agreement--service":{"id":"components-user-agreement--service","name":"service","title":"Components/User Agreement","importPath":"./src/user-agreement/user-agreement.stories.tsx","tags":["story"],"kind":"Components/User Agreement","story":"service","parameters":{"__id":"components-user-agreement--service","docsOnly":false,"fileName":"./src/user-agreement/user-agreement.stories.tsx"}},"components-user-card--inline":{"id":"components-user-card--inline","name":"inline","title":"Components/User Card","importPath":"./src/user-card/user-card.stories.tsx","tags":["story"],"kind":"Components/User Card","story":"inline","parameters":{"__id":"components-user-card--inline","docsOnly":false,"fileName":"./src/user-card/user-card.stories.tsx"}},"components-user-card--smart-tooltip":{"id":"components-user-card--smart-tooltip","name":"smart tooltip","title":"Components/User Card","importPath":"./src/user-card/user-card.stories.tsx","tags":["story"],"kind":"Components/User Card","story":"smart tooltip","parameters":{"__id":"components-user-card--smart-tooltip","docsOnly":false,"fileName":"./src/user-card/user-card.stories.tsx"}},"components-user-card--hub-user-card":{"id":"components-user-card--hub-user-card","name":"hub user card","title":"Components/User Card","importPath":"./src/user-card/user-card.stories.tsx","tags":["story"],"kind":"Components/User Card","story":"hub user card","parameters":{"__id":"components-user-card--hub-user-card","docsOnly":false,"fileName":"./src/user-card/user-card.stories.tsx"}}}}
